joshbasiccalculator/__init__.py
alibaidhani-0.0.1.dist-info/LICENCE.txt
alibaidhani-0.0.1.dist-info/METADATA
alibaidhani-0.0.1.dist-info/WHEEL
alibaidhani-0.0.1.dist-info/top_level.txt
alibaidhani-0.0.1.dist-info/RECORD
